docov/__init__.py
docov/__main__.py
docov/docov.py
docov-0.0.3.dist-info/LICENSE
docov-0.0.3.dist-info/METADATA
docov-0.0.3.dist-info/WHEEL
docov-0.0.3.dist-info/entry_points.txt
docov-0.0.3.dist-info/top_level.txt
docov-0.0.3.dist-info/RECORD
