Metadata-Version: 2.1
Name: docov
Version: 0.0.3
Summary: Light-weight docstring coverage analysis for python modules
Home-page: https://github.com/ripaul/docov
Author: Richard D. Paul
Author-email: r.paul@fz-juelich.de
License: UNKNOWN
Project-URL: Bug Reports, https://github.com/ripaul/docov/issues
Project-URL: Source, https://github.com/ripaul/docov/
Keywords: coverage,development
Platform: UNKNOWN
Classifier: Development Status :: 3 - Alpha
Classifier: Intended Audience :: Developers
Classifier: Topic :: Software Development :: Build Tools
Classifier: License :: OSI Approved :: MIT License
Classifier: Programming Language :: Python :: 3
Classifier: Programming Language :: Python :: 3.6
Classifier: Programming Language :: Python :: 3.7
Classifier: Programming Language :: Python :: 3.8
Classifier: Programming Language :: Python :: 3.9
Classifier: Programming Language :: Python :: 3.10
Classifier: Programming Language :: Python :: 3 :: Only
Requires-Python: >=3.6, <4
Requires-Dist: anybadge
Requires-Dist: argparse
